plenario_exporter_s3/__init__.py
plenario_exporter_s3/admin.py
plenario_exporter_s3/apps.py
plenario_exporter_s3/consumers.py
plenario_exporter_s3/defaults.py
plenario_exporter_s3/enums.py
plenario_exporter_s3/models.py
plenario_exporter_s3/routing.py
plenario_exporter_s3/services.py
plenario_exporter_s3/migrations/0001_initial.py
plenario_exporter_s3/migrations/0002_auto_20170922_1635.py
plenario_exporter_s3/migrations/0003_auto_20170922_1722.py
plenario_exporter_s3/migrations/0004_auto_20170922_1942.py
plenario_exporter_s3/migrations/0005_auto_20170922_2037.py
plenario_exporter_s3/migrations/0006_auto_20170922_2046.py
plenario_exporter_s3/migrations/__init__.py
plenario_exporter_s3/tests/__init__.py
plenario_exporter_s3/tests/test_consumers.py
plenario_exporter_s3/tests/test_services.py
plenario_exporter_s3-0.0.4.dist-info/DESCRIPTION.rst
plenario_exporter_s3-0.0.4.dist-info/METADATA
plenario_exporter_s3-0.0.4.dist-info/RECORD
plenario_exporter_s3-0.0.4.dist-info/WHEEL
plenario_exporter_s3-0.0.4.dist-info/metadata.json
plenario_exporter_s3-0.0.4.dist-info/top_level.txt
tests/app/__init__.py
tests/app/apps.py
tests/app/models.py
tests/app/views.py
tests/app/migrations/0001_initial.py
tests/app/migrations/__init__.py
