Metadata-Version: 2.0
Name: plenario-exporter-s3
Version: 0.0.4
Summary: export pleanrio data sets to s3
Home-page: https://github.com/UrbanCCD-UChicago/plenario-exporter-s3
Author: Vince Forgione
Author-email: vforgione@uhicago.edu
License: GPLv3
Keywords: plenario
Platform: UNKNOWN
Classifier: Development Status :: 3 - Alpha
Classifier: License :: OSI Approved :: GNU General Public License v3 (GPLv3)
Classifier: Programming Language :: Python :: 3.6
Requires-Python: >=3.6
Requires-Dist: Django (<1.12,>=1.11)
Requires-Dist: channels
Requires-Dist: asgi-redis
Requires-Dist: arrow
Requires-Dist: boto3
